cook/__init__.py
cook/__main__.py
cook/_version.py
cook/config.py
cook/executor.py
cook/io_helper.py
cook/progress.py
cook/subprocess.py
cook/util.py
cook_executor-0.1.19.dist-info/METADATA
cook_executor-0.1.19.dist-info/WHEEL
cook_executor-0.1.19.dist-info/entry_points.txt
cook_executor-0.1.19.dist-info/top_level.txt
cook_executor-0.1.19.dist-info/RECORD
