Metadata-Version: 2.1
Name: cook-executor
Version: 0.1.19
Summary: Custom Mesos executor for Cook written in Python
Home-page: https://github.com/twosigma/Cook
License: Apache Software License 2.0
Keywords: cook-executor
Platform: UNKNOWN
Classifier: Programming Language :: Python :: 3.5
Requires-Dist: psutil (==5.4.1)
Requires-Dist: pymesos (==0.3.12)
Provides-Extra: test
Requires-Dist: pytest (==5.2.0) ; extra == 'test'
Requires-Dist: pytest-timeout (==1.3.3) ; extra == 'test'
Requires-Dist: pytest-xdist (==1.30.0) ; extra == 'test'
